trovesuite_auth_service/__init__.py
trovesuite_auth_service/auth_base.py
trovesuite_auth_service/auth_read_dto.py
trovesuite_auth_service/auth_service.py
trovesuite_auth_service/configs/__init__.py
trovesuite_auth_service/configs/database.py
trovesuite_auth_service/configs/logging.py
trovesuite_auth_service/configs/settings.py
trovesuite_auth_service/entities/__init__.py
trovesuite_auth_service/entities/shared_response.py
trovesuite_auth_service/utils/__init__.py
trovesuite_auth_service/utils/helper.py
trovesuite_auth_service-1.0.8.dist-info/licenses/LICENSE
trovesuite_auth_service-1.0.8.dist-info/METADATA
trovesuite_auth_service-1.0.8.dist-info/WHEEL
trovesuite_auth_service-1.0.8.dist-info/top_level.txt
trovesuite_auth_service-1.0.8.dist-info/RECORD
