Metadata-Version: 2.4
Name: trovesuite-auth-service
Version: 1.0.8
Summary: A comprehensive authentication and authorization service for ERP systems
Home-page: https://github.com/deladetech/trovesuite-auth-service
Author: Bright Debrah Owusu
Author-email: Bright Debrah Owusu <owusu.debrah@deladetech.com>
Maintainer-email: Bright Debrah Owusu <owusu.debrah@deladetech.com>
License: MIT
Project-URL: Homepage, https://github.com/deladetech/trovesuite-auth-service
Project-URL: Repository, https://github.com/deladetech/trovesuite-auth-service
Project-URL: Documentation, https://github.com/deladetech/trovesuite-auth-service#readme
Project-URL: Bug Tracker, https://github.com/deladetech/trovesuite-auth-service/issues
Keywords: authentication,authorization,jwt,erp,fastapi,security
Classifier: Development Status :: 5 - Production/Stable
Classifier: Intended Audience :: Developers
Classifier: License :: OSI Approved :: MIT License
Classifier: Operating System :: OS Independent
Classifier: Programming Language :: Python :: 3
Classifier: Programming Language :: Python :: 3.11
Classifier: Programming Language :: Python :: 3.12
Classifier: Programming Language :: Python :: 3.13
Classifier: Topic :: Software Development :: Libraries :: Python Modules
Classifier: Topic :: Internet :: WWW/HTTP :: Dynamic Content
Classifier: Topic :: Security
Requires-Python: >=3.12
License-File: LICENSE
Requires-Dist: fastapi>=0.116.1
Requires-Dist: pydantic>=2.11.9
Requires-Dist: psycopg2-binary>=2.9.9
Requires-Dist: python-dotenv>=1.0.0
Requires-Dist: python-multipart>=0.0.6
Requires-Dist: python-jose[cryptography]>=3.3.0
Requires-Dist: passlib[bcrypt]>=1.7.4
Requires-Dist: passlib[argon2]<2.0.0,>=1.7.4
Provides-Extra: dev
Requires-Dist: pytest>=8.4.2; extra == "dev"
Requires-Dist: pytest-asyncio>=0.21.1; extra == "dev"
Requires-Dist: pytest-cov>=4.1.0; extra == "dev"
Requires-Dist: pytest-mock>=3.12.0; extra == "dev"
Requires-Dist: factory-boy>=3.3.0; extra == "dev"
Requires-Dist: faker>=20.1.0; extra == "dev"
Requires-Dist: black>=23.11.0; extra == "dev"
Requires-Dist: mypy>=1.0.0; extra == "dev"
Requires-Dist: flake8>=6.0.0; extra == "dev"
Dynamic: author
Dynamic: home-page
Dynamic: license-file
Dynamic: requires-python
